flamapy/interfaces/__init__.py
flamapy/interfaces/command_line/__init__.py
flamapy/interfaces/python/FLAMAFeatureModel.py
flamapy/interfaces/python/__init__.py
flamapy/interfaces/rest/operations_routes.py
flamapy_fm_dist-1.6.0.dist-info/LICENSE
flamapy_fm_dist-1.6.0.dist-info/METADATA
flamapy_fm_dist-1.6.0.dist-info/WHEEL
flamapy_fm_dist-1.6.0.dist-info/entry_points.txt
flamapy_fm_dist-1.6.0.dist-info/top_level.txt
flamapy_fm_dist-1.6.0.dist-info/RECORD
