Metadata-Version: 2.1
Name: flamapy-fm-dist
Version: 1.6.0
Summary: Flamapy feature model is a distribution of the flama framework containing all plugins required to analyze feature models. It also offers a richier API and a complete command line interface and documentation.
Home-page: https://github.com/flamapy/flamapy-feature-model
Author: Flamapy
Author-email: flamapy@us.es
License: UNKNOWN
Platform: UNKNOWN
Classifier: Programming Language :: Python :: 3
Classifier: License :: OSI Approved :: GNU General Public License v3 or later (GPLv3+)
Classifier: Operating System :: OS Independent
Requires-Python: >=3.9
License-File: LICENSE
Requires-Dist: wheel
Requires-Dist: Flask
Requires-Dist: gunicorn
Requires-Dist: flamapy
Requires-Dist: flamapy-fm
Requires-Dist: flamapy-sat
Requires-Dist: flask-swagger-ui
Requires-Dist: flask-restplus
Requires-Dist: pytest
Requires-Dist: flask-cors
Requires-Dist: flasgger
Requires-Dist: Fire
Provides-Extra: dev
Requires-Dist: pytest ; extra == 'dev'
Requires-Dist: pytest-mock ; extra == 'dev'
Requires-Dist: prospector ; extra == 'dev'
Requires-Dist: mypy ; extra == 'dev'
Requires-Dist: coverage ; extra == 'dev'
